scriptmaker/__init__.py
scriptmaker/__main__.py
scriptmaker/constants.py
scriptmaker/data/__init__.py
scriptmaker/data/compiled/__init__.py
scriptmaker/data/compiled/nightmeta.json
scriptmaker/data/compiled/official.json
scriptmaker/data/datastore.py
scriptmaker/data/icon.py
scriptmaker/data/icons/Icon_DAWN.png
scriptmaker/data/icons/Icon_DEMON.png
scriptmaker/data/icons/Icon_DUSK.png
scriptmaker/data/icons/Icon_MINION.png
scriptmaker/data/icons/Icon_acrobat.png
scriptmaker/data/icons/Icon_alchemist.png
scriptmaker/data/icons/Icon_alhadikhia.png
scriptmaker/data/icons/Icon_alsaahir.png
scriptmaker/data/icons/Icon_amnesiac.png
scriptmaker/data/icons/Icon_angel.png
scriptmaker/data/icons/Icon_apprentice.png
scriptmaker/data/icons/Icon_artist.png
scriptmaker/data/icons/Icon_assassin.png
scriptmaker/data/icons/Icon_atheist.png
scriptmaker/data/icons/Icon_balloonist.png
scriptmaker/data/icons/Icon_banshee.png
scriptmaker/data/icons/Icon_barber.png
scriptmaker/data/icons/Icon_barista.png
scriptmaker/data/icons/Icon_baron.png
scriptmaker/data/icons/Icon_beggar.png
scriptmaker/data/icons/Icon_bishop.png
scriptmaker/data/icons/Icon_boffin.png
scriptmaker/data/icons/Icon_bonecollector.png
scriptmaker/data/icons/Icon_boomdandy.png
scriptmaker/data/icons/Icon_bootlegger.png
scriptmaker/data/icons/Icon_bountyhunter.png
scriptmaker/data/icons/Icon_buddhist.png
scriptmaker/data/icons/Icon_bureaucrat.png
scriptmaker/data/icons/Icon_butcher.png
scriptmaker/data/icons/Icon_butler.png
scriptmaker/data/icons/Icon_cannibal.png
scriptmaker/data/icons/Icon_cerenovus.png
scriptmaker/data/icons/Icon_chambermaid.png
scriptmaker/data/icons/Icon_chef.png
scriptmaker/data/icons/Icon_choirboy.png
scriptmaker/data/icons/Icon_clockmaker.png
scriptmaker/data/icons/Icon_courtier.png
scriptmaker/data/icons/Icon_cultleader.png
scriptmaker/data/icons/Icon_damsel.png
scriptmaker/data/icons/Icon_deviant.png
scriptmaker/data/icons/Icon_devilsadvocate.png
scriptmaker/data/icons/Icon_djinn.png
scriptmaker-2.1.0.dist-info/METADATA
scriptmaker-2.1.0.dist-info/WHEEL
scriptmaker-2.1.0.dist-info/RECORD
