Metadata-Version: 2.1
Name: scriptmaker
Version: 2.1.0
Summary: A Python library for producing custom scripts in Blood On The Clocktower.
License: MIT
Author: Rohan Sarvaria
Author-email: rsarvaria@uwaterloo.ca
Requires-Python: >=3.11,<4.0
Classifier: License :: OSI Approved :: MIT License
Classifier: Programming Language :: Python :: 3
Classifier: Programming Language :: Python :: 3.11
Classifier: Programming Language :: Python :: 3.12
Requires-Dist: drawsvg[all] (>=2.3.0,<3.0.0)
Requires-Dist: jinja2 (>=3.1.2,<4.0.0)
Requires-Dist: pdf2image (>=1.16.3,<2.0.0)
Requires-Dist: pillow (>=10.1.0,<11.0.0)
Requires-Dist: pip (>=24.3.1,<25.0.0)
Requires-Dist: pyyaml (>=6.0.2,<7.0.0)
Requires-Dist: weasyprint (>=62,<63)
